README.rst
setup.cfg
setup.py
dbio/__init__.py
dbio/__main__.py
dbio/io.py
dbio.egg-info/PKG-INFO
dbio.egg-info/SOURCES.txt
dbio.egg-info/dependency_links.txt
dbio.egg-info/entry_points.txt
dbio.egg-info/requires.txt
dbio.egg-info/top_level.txt
dbio/databases/__init__.py
dbio/databases/base.py
dbio/databases/mysql.py
dbio/databases/postgresql.py
dbio/databases/sqlite.py
dbio/databases/vertica.py