Metadata-Version: 1.1
Name: dbio
Version: 0.4.8
Summary: Simple module for database I/O operations.
Home-page: https://github.com/locusenergy/dbio
Author: Locus Energy
Author-email: dbio@locusenergy.com
License: MIT
Download-URL: https://github.com/LocusEnergy/dbio/tarball/0.4.4
Platform: UNKNOWN
Classifier: Development Status :: 3 - Alpha
Classifier: Intended Audience :: Developers
Classifier: License :: OSI Approved :: MIT License
Classifier: Programming Language :: Python :: 2.7
Classifier: Topic :: Database
